{
  "2011-12-07": {
    "min": 700.0,
    "max": 800.0,
    "modal": 750.0,
    "arrival": 110.0,
    "arrive_unit": "Tonnes",
    "price_unit": "Rs/Quintal",
    "variety": "Other"
  },
  "2011-12-08": {
    "min": 700.0,
    "max": 800.0,
    "modal": 750.0,
    "arrival": 140.0,
    "arrive_unit": "Tonnes",
    "price_unit": "Rs/Quintal",
    "variety": "Other"
  },
  "2011-12-09": {
    "min": 700.0,
    "max": 800.0,
    "modal": 750.0,
    "arrival": 130.0,
    "arrive_unit": "Tonnes",
    "price_unit": "Rs/Quintal",
    "variety": "Other"
  },
  "2011-12-10": {
    "min": 700.0,
    "max": 800.0,
    "modal": 750.0,
    "arrival": 140.0,
    "arrive_unit": "Tonnes",
    "price_unit": "Rs/Quintal",
    "variety": "Other"
  },
  "2011-12-11": {
    "min": 700.0,
    "max": 800.0,
    "modal": 750.0,
    "arrival": 121.0,
    "arrive_unit": "Tonnes",
    "price_unit": "Rs/Quintal",
    "variety": "Other"
  },
  "2011-12-12": {
    "min": 700.0,
    "max": 800.0,
    "modal": 750.0,
    "arrival": 180.0,
    "arrive_unit": "Tonnes",
    "price_unit": "Rs/Quintal",
    "variety": "Other"
  },
  "2011-12-13": {
    "min": 550.0,
    "max": 650.0,
    "modal": 600.0,
    "arrival": 150.0,
    "arrive_unit": "Tonnes",
    "price_unit": "Rs/Quintal",
    "variety": "Other"
  },
  "2011-12-14": {
    "min": 550.0,
    "max": 650.0,
    "modal": 600.0,
    "arrival": 140.0,
    "arrive_unit": "Tonnes",
    "price_unit": "Rs/Quintal",
    "variety": "Other"
  },
  "2011-12-15": {
    "min": 450.0,
    "max": 550.0,
    "modal": 500.0,
    "arrival": 150.0,
    "arrive_unit": "Tonnes",
    "price_unit": "Rs/Quintal",
    "variety": "Other"
  },
  "2011-12-16": {
    "min": 450.0,
    "max": 550.0,
    "modal": 500.0,
    "arrival": 160.0,
    "arrive_unit": "Tonnes",
    "price_unit": "Rs/Quintal",
    "variety": "Other"
  },
  "2011-12-17": {
    "min": 450.0,
    "max": 550.0,
    "modal": 500.0,
    "arrival": 160.0,
    "arrive_unit": "Tonnes",
    "price_unit": "Rs/Quintal",
    "variety": "Other"
  },
  "2011-12-18": {
    "min": 450.0,
    "max": 550.0,
    "modal": 500.0,
    "arrival": 150.0,
    "arrive_unit": "Tonnes",
    "price_unit": "Rs/Quintal",
    "variety": "Other"
  },
  "2011-12-19": {
    "min": 450.0,
    "max": 550.0,
    "modal": 500.0,
    "arrival": 140.0,
    "arrive_unit": "Tonnes",
    "price_unit": "Rs/Quintal",
    "variety": "Other"
  },
  "2011-12-20": {
    "min": 450.0,
    "max": 550.0,
    "modal": 500.0,
    "arrival": 130.0,
    "arrive_unit": "Tonnes",
    "price_unit": "Rs/Quintal",
    "variety": "Other"
  },
  "2011-12-21": {
    "min": 450.0,
    "max": 550.0,
    "modal": 500.0,
    "arrival": 140.0,
    "arrive_unit": "Tonnes",
    "price_unit": "Rs/Quintal",
    "variety": "Other"
  },
  "2011-12-22": {
    "min": 450.0,
    "max": 550.0,
    "modal": 500.0,
    "arrival": 170.0,
    "arrive_unit": "Tonnes",
    "price_unit": "Rs/Quintal",
    "variety": "Other"
  },
  "2011-12-23": {
    "min": 450.0,
    "max": 550.0,
    "modal": 500.0,
    "arrival": 140.0,
    "arrive_unit": "Tonnes",
    "price_unit": "Rs/Quintal",
    "variety": "Other"
  },
  "2011-12-24": {
    "min": 550.0,
    "max": 650.0,
    "modal": 600.0,
    "arrival": 180.0,
    "arrive_unit": "Tonnes",
    "price_unit": "Rs/Quintal",
    "variety": "Other"
  },
  "2011-12-25": {
    "min": 550.0,
    "max": 650.0,
    "modal": 600.0,
    "arrival": 140.0,
    "arrive_unit": "Tonnes",
    "price_unit": "Rs/Quintal",
    "variety": "Other"
  },
  "2011-12-26": {
    "min": 550.0,
    "max": 650.0,
    "modal": 600.0,
    "arrival": 150.0,
    "arrive_unit": "Tonnes",
    "price_unit": "Rs/Quintal",
    "variety": "Other"
  },
  "2011-12-27": {
    "min": 550.0,
    "max": 650.0,
    "modal": 600.0,
    "arrival": 140.0,
    "arrive_unit": "Tonnes",
    "price_unit": "Rs/Quintal",
    "variety": "Other"
  },
  "2011-12-28": {
    "min": 550.0,
    "max": 650.0,
    "modal": 600.0,
    "arrival": 160.0,
    "arrive_unit": "Tonnes",
    "price_unit": "Rs/Quintal",
    "variety": "Other"
  },
  "2011-12-29": {
    "min": 550.0,
    "max": 650.0,
    "modal": 600.0,
    "arrival": 140.0,
    "arrive_unit": "Tonnes",
    "price_unit": "Rs/Quintal",
    "variety": "Other"
  },
  "2011-12-30": {
    "min": 550.0,
    "max": 650.0,
    "modal": 600.0,
    "arrival": 130.0,
    "arrive_unit": "Tonnes",
    "price_unit": "Rs/Quintal",
    "variety": "Other"
  }
}