{
  "2011-07-01": {
    "min": 200.0,
    "max": 500.0,
    "modal": 350.0,
    "arrival": 25.55,
    "arrive_unit": "Tonnes",
    "price_unit": "Rs/Quintal",
    "variety": "Other"
  },
  "2011-07-02": {
    "min": 200.0,
    "max": 500.0,
    "modal": 350.0,
    "arrival": 62.76,
    "arrive_unit": "Tonnes",
    "price_unit": "Rs/Quintal",
    "variety": "Other"
  },
  "2011-07-03": {
    "min": 200.0,
    "max": 500.0,
    "modal": 350.0,
    "arrival": 25.16,
    "arrive_unit": "Tonnes",
    "price_unit": "Rs/Quintal",
    "variety": "Other"
  },
  "2011-07-04": {
    "min": 300.0,
    "max": 500.0,
    "modal": 400.0,
    "arrival": 31.16,
    "arrive_unit": "Tonnes",
    "price_unit": "Rs/Quintal",
    "variety": "Other"
  },
  "2011-07-05": {
    "min": 300.0,
    "max": 500.0,
    "modal": 400.0,
    "arrival": 31.16,
    "arrive_unit": "Tonnes",
    "price_unit": "Rs/Quintal",
    "variety": "Other"
  },
  "2011-07-07": {
    "min": 300.0,
    "max": 500.0,
    "modal": 400.0,
    "arrival": 81.2,
    "arrive_unit": "Tonnes",
    "price_unit": "Rs/Quintal",
    "variety": "Other"
  },
  "2011-07-08": {
    "min": 300.0,
    "max": 600.0,
    "modal": 450.0,
    "arrival": 11.4,
    "arrive_unit": "Tonnes",
    "price_unit": "Rs/Quintal",
    "variety": "Other"
  },
  "2011-07-09": {
    "min": 300.0,
    "max": 500.0,
    "modal": 400.0,
    "arrival": 45.5,
    "arrive_unit": "Tonnes",
    "price_unit": "Rs/Quintal",
    "variety": "Other"
  },
  "2011-07-10": {
    "min": 300.0,
    "max": 500.0,
    "modal": 400.0,
    "arrival": 1.26,
    "arrive_unit": "Tonnes",
    "price_unit": "Rs/Quintal",
    "variety": "Other"
  },
  "2011-07-11": {
    "min": 400.0,
    "max": 700.0,
    "modal": 550.0,
    "arrival": 31.6,
    "arrive_unit": "Tonnes",
    "price_unit": "Rs/Quintal",
    "variety": "Other"
  },
  "2011-07-12": {
    "min": 400.0,
    "max": 700.0,
    "modal": 550.0,
    "arrival": 11.7,
    "arrive_unit": "Tonnes",
    "price_unit": "Rs/Quintal",
    "variety": "Other"
  },
  "2011-07-14": {
    "min": 300.0,
    "max": 500.0,
    "modal": 400.0,
    "arrival": 10.85,
    "arrive_unit": "Tonnes",
    "price_unit": "Rs/Quintal",
    "variety": "Other"
  },
  "2011-07-15": {
    "min": 300.0,
    "max": 500.0,
    "modal": 400.0,
    "arrival": 41.71,
    "arrive_unit": "Tonnes",
    "price_unit": "Rs/Quintal",
    "variety": "Other"
  },
  "2011-07-16": {
    "min": 300.0,
    "max": 500.0,
    "modal": 400.0,
    "arrival": 15.03,
    "arrive_unit": "Tonnes",
    "price_unit": "Rs/Quintal",
    "variety": "Other"
  },
  "2011-07-17": {
    "min": 300.0,
    "max": 500.0,
    "modal": 400.0,
    "arrival": 3.8,
    "arrive_unit": "Tonnes",
    "price_unit": "Rs/Quintal",
    "variety": "Other"
  },
  "2011-07-18": {
    "min": 300.0,
    "max": 500.0,
    "modal": 400.0,
    "arrival": 72.45,
    "arrive_unit": "Tonnes",
    "price_unit": "Rs/Quintal",
    "variety": "Other"
  },
  "2011-07-19": {
    "min": 300.0,
    "max": 500.0,
    "modal": 400.0,
    "arrival": 39.35,
    "arrive_unit": "Tonnes",
    "price_unit": "Rs/Quintal",
    "variety": "Other"
  },
  "2011-07-21": {
    "min": 300.0,
    "max": 500.0,
    "modal": 400.0,
    "arrival": 7.13,
    "arrive_unit": "Tonnes",
    "price_unit": "Rs/Quintal",
    "variety": "Other"
  },
  "2011-07-22": {
    "min": 300.0,
    "max": 600.0,
    "modal": 450.0,
    "arrival": 22.3,
    "arrive_unit": "Tonnes",
    "price_unit": "Rs/Quintal",
    "variety": "Other"
  },
  "2011-07-23": {
    "min": 300.0,
    "max": 600.0,
    "modal": 450.0,
    "arrival": 24.65,
    "arrive_unit": "Tonnes",
    "price_unit": "Rs/Quintal",
    "variety": "Other"
  },
  "2011-07-24": {
    "min": 300.0,
    "max": 600.0,
    "modal": 450.0,
    "arrival": 3.96,
    "arrive_unit": "Tonnes",
    "price_unit": "Rs/Quintal",
    "variety": "Other"
  },
  "2011-07-25": {
    "min": 400.0,
    "max": 600.0,
    "modal": 500.0,
    "arrival": 17.46,
    "arrive_unit": "Tonnes",
    "price_unit": "Rs/Quintal",
    "variety": "Other"
  },
  "2011-07-26": {
    "min": 400.0,
    "max": 600.0,
    "modal": 500.0,
    "arrival": 15.55,
    "arrive_unit": "Tonnes",
    "price_unit": "Rs/Quintal",
    "variety": "Other"
  },
  "2011-07-28": {
    "min": 400.0,
    "max": 600.0,
    "modal": 500.0,
    "arrival": 1.88,
    "arrive_unit": "Tonnes",
    "price_unit": "Rs/Quintal",
    "variety": "Other"
  },
  "2011-07-29": {
    "min": 400.0,
    "max": 600.0,
    "modal": 500.0,
    "arrival": 3.6,
    "arrive_unit": "Tonnes",
    "price_unit": "Rs/Quintal",
    "variety": "Other"
  },
  "2011-07-30": {
    "min": 400.0,
    "max": 600.0,
    "modal": 500.0,
    "arrival": 26.1,
    "arrive_unit": "Tonnes",
    "price_unit": "Rs/Quintal",
    "variety": "Other"
  },
  "2011-07-31": {
    "min": 400.0,
    "max": 600.0,
    "modal": 500.0,
    "arrival": 25.16,
    "arrive_unit": "Tonnes",
    "price_unit": "Rs/Quintal",
    "variety": "Other"
  }
}