{
  "2015-05-04": {
    "min": 11.0,
    "max": 21.0,
    "modal": 15.0,
    "arrival": 300.0,
    "arrive_unit": "Nos",
    "price_unit": "Rs/Number",
    "variety": "Other"
  },
  "2015-05-07": {
    "min": 6.0,
    "max": 12.0,
    "modal": 10.966666666666667,
    "arrival": 200.0,
    "arrive_unit": "Nos",
    "price_unit": "Rs/Number",
    "variety": "Other"
  },
  "2015-05-12": {
    "min": 12.0,
    "max": 18.0,
    "modal": 16.0,
    "arrival": 300.0,
    "arrive_unit": "Nos",
    "price_unit": "Rs/Number",
    "variety": "Other"
  },
  "2015-05-13": {
    "min": 122.5,
    "max": 167.5,
    "modal": 156.0,
    "arrival": 50.0,
    "arrive_unit": "Nos",
    "price_unit": "Rs/Quintal",
    "variety": "Other"
  },
  "2015-05-17": {
    "min": 52.0,
    "max": 80.0,
    "modal": 68.0,
    "arrival": 50.0,
    "arrive_unit": "Nos",
    "price_unit": "Rs/Quintal",
    "variety": "Other"
  },
  "2015-05-21": {
    "min": 12.0,
    "max": 20.0,
    "modal": 18.0,
    "arrival": 500.0,
    "arrive_unit": "Nos",
    "price_unit": "Rs/Number",
    "variety": "Other"
  },
  "2015-05-23": {
    "min": 12.0,
    "max": 18.0,
    "modal": 16.0,
    "arrival": 400.0,
    "arrive_unit": "Nos",
    "price_unit": "Rs/Number",
    "variety": "Other"
  },
  "2015-05-25": {
    "min": 10.0,
    "max": 20.0,
    "modal": 16.0,
    "arrival": 200.0,
    "arrive_unit": "Nos",
    "price_unit": "Rs/Number",
    "variety": "Other"
  },
  "2015-05-27": {
    "min": 126.66666666666667,
    "max": 200.0,
    "modal": 183.33333333333334,
    "arrival": 225.0,
    "arrive_unit": "Nos",
    "price_unit": "Rs/Quintal",
    "variety": "Other"
  },
  "2015-05-28": {
    "min": 12.0,
    "max": 20.0,
    "modal": 18.0,
    "arrival": 200.0,
    "arrive_unit": "Nos",
    "price_unit": "Rs/Number",
    "variety": "Other"
  },
  "2015-05-31": {
    "min": 90.0,
    "max": 120.0,
    "modal": 115.0,
    "arrival": 75.0,
    "arrive_unit": "Nos",
    "price_unit": "Rs/Quintal",
    "variety": "Other"
  }
}