{
  "2013-10-01": {
    "min": 3402.0,
    "max": 3526.0,
    "modal": 3464.0,
    "arrival": 25.7,
    "arrive_unit": "Tonnes",
    "price_unit": "Rs/Quintal",
    "variety": "Other"
  },
  "2013-10-02": {
    "min": 3321.0,
    "max": 3521.0,
    "modal": 3421.0,
    "arrival": 32.1,
    "arrive_unit": "Tonnes",
    "price_unit": "Rs/Quintal",
    "variety": "Other"
  },
  "2013-10-03": {
    "min": 3200.0,
    "max": 3498.0,
    "modal": 3349.0,
    "arrival": 29.3,
    "arrive_unit": "Tonnes",
    "price_unit": "Rs/Quintal",
    "variety": "Other"
  },
  "2013-10-04": {
    "min": 3250.0,
    "max": 3545.0,
    "modal": 3398.0,
    "arrival": 18.4,
    "arrive_unit": "Tonnes",
    "price_unit": "Rs/Quintal",
    "variety": "Other"
  },
  "2013-10-05": {
    "min": 3102.0,
    "max": 3320.0,
    "modal": 3211.0,
    "arrival": 4.0,
    "arrive_unit": "Tonnes",
    "price_unit": "Rs/Quintal",
    "variety": "Other"
  },
  "2013-10-07": {
    "min": 3395.0,
    "max": 3525.0,
    "modal": 3460.0,
    "arrival": 30.0,
    "arrive_unit": "Tonnes",
    "price_unit": "Rs/Quintal",
    "variety": "Other"
  },
  "2013-10-09": {
    "min": 3225.0,
    "max": 3351.0,
    "modal": 3288.0,
    "arrival": 29.7,
    "arrive_unit": "Tonnes",
    "price_unit": "Rs/Quintal",
    "variety": "Other"
  },
  "2013-10-10": {
    "min": 3275.0,
    "max": 3485.0,
    "modal": 3363.0,
    "arrival": 27.2,
    "arrive_unit": "Tonnes",
    "price_unit": "Rs/Quintal",
    "variety": "Other"
  },
  "2013-10-11": {
    "min": 3200.0,
    "max": 3500.0,
    "modal": 3350.0,
    "arrival": 18.0,
    "arrive_unit": "Tonnes",
    "price_unit": "Rs/Quintal",
    "variety": "Other"
  },
  "2013-10-12": {
    "min": 3300.0,
    "max": 3478.0,
    "modal": 3390.0,
    "arrival": 14.0,
    "arrive_unit": "Tonnes",
    "price_unit": "Rs/Quintal",
    "variety": "Other"
  },
  "2013-10-14": {
    "min": 3251.0,
    "max": 3565.0,
    "modal": 3408.0,
    "arrival": 6.9,
    "arrive_unit": "Tonnes",
    "price_unit": "Rs/Quintal",
    "variety": "Other"
  },
  "2013-10-15": {
    "min": 3370.0,
    "max": 3565.0,
    "modal": 3468.0,
    "arrival": 6.3,
    "arrive_unit": "Tonnes",
    "price_unit": "Rs/Quintal",
    "variety": "Other"
  },
  "2013-10-16": {
    "min": 3300.0,
    "max": 3594.0,
    "modal": 3447.0,
    "arrival": 8.7,
    "arrive_unit": "Tonnes",
    "price_unit": "Rs/Quintal",
    "variety": "Other"
  },
  "2013-10-17": {
    "min": 3351.0,
    "max": 3624.0,
    "modal": 3488.0,
    "arrival": 11.2,
    "arrive_unit": "Tonnes",
    "price_unit": "Rs/Quintal",
    "variety": "Other"
  },
  "2013-10-18": {
    "min": 3350.0,
    "max": 3660.0,
    "modal": 3505.0,
    "arrival": 7.8,
    "arrive_unit": "Tonnes",
    "price_unit": "Rs/Quintal",
    "variety": "Other"
  },
  "2013-10-19": {
    "min": 3301.0,
    "max": 3710.0,
    "modal": 3506.0,
    "arrival": 6.9,
    "arrive_unit": "Tonnes",
    "price_unit": "Rs/Quintal",
    "variety": "Other"
  },
  "2013-10-21": {
    "min": 3450.0,
    "max": 3770.0,
    "modal": 3610.0,
    "arrival": 14.2,
    "arrive_unit": "Tonnes",
    "price_unit": "Rs/Quintal",
    "variety": "Other"
  },
  "2013-10-22": {
    "min": 3000.0,
    "max": 3987.0,
    "modal": 3493.0,
    "arrival": 11.3,
    "arrive_unit": "Tonnes",
    "price_unit": "Rs/Quintal",
    "variety": "Other"
  },
  "2013-10-23": {
    "min": 3280.0,
    "max": 3926.0,
    "modal": 3603.0,
    "arrival": 15.3,
    "arrive_unit": "Tonnes",
    "price_unit": "Rs/Quintal",
    "variety": "Other"
  },
  "2013-10-24": {
    "min": 3500.0,
    "max": 3900.0,
    "modal": 3700.0,
    "arrival": 10.2,
    "arrive_unit": "Tonnes",
    "price_unit": "Rs/Quintal",
    "variety": "Other"
  },
  "2013-10-25": {
    "min": 3550.0,
    "max": 3866.0,
    "modal": 3708.0,
    "arrival": 20.6,
    "arrive_unit": "Tonnes",
    "price_unit": "Rs/Quintal",
    "variety": "Other"
  },
  "2013-10-26": {
    "min": 3691.0,
    "max": 3940.0,
    "modal": 3815.0,
    "arrival": 10.9,
    "arrive_unit": "Tonnes",
    "price_unit": "Rs/Quintal",
    "variety": "Other"
  },
  "2013-10-28": {
    "min": 3701.0,
    "max": 4037.0,
    "modal": 3869.0,
    "arrival": 7.0,
    "arrive_unit": "Tonnes",
    "price_unit": "Rs/Quintal",
    "variety": "Other"
  },
  "2013-10-29": {
    "min": 3650.0,
    "max": 4020.0,
    "modal": 3835.0,
    "arrival": 12.6,
    "arrive_unit": "Tonnes",
    "price_unit": "Rs/Quintal",
    "variety": "Other"
  },
  "2013-10-30": {
    "min": 3660.0,
    "max": 3925.0,
    "modal": 3793.0,
    "arrival": 7.7,
    "arrive_unit": "Tonnes",
    "price_unit": "Rs/Quintal",
    "variety": "Other"
  },
  "2013-10-31": {
    "min": 3725.0,
    "max": 3821.0,
    "modal": 3773.0,
    "arrival": 4.7,
    "arrive_unit": "Tonnes",
    "price_unit": "Rs/Quintal",
    "variety": "Other"
  }
}