{
  "2014-08-01": {
    "min": 10400.0,
    "max": 10600.0,
    "modal": 10500.0,
    "arrival": 3.5,
    "arrive_unit": "Tonnes",
    "price_unit": "Rs/Quintal",
    "variety": "Other"
  },
  "2014-08-04": {
    "min": 10200.0,
    "max": 10400.0,
    "modal": 10300.0,
    "arrival": 1.8,
    "arrive_unit": "Tonnes",
    "price_unit": "Rs/Quintal",
    "variety": "Other"
  },
  "2014-08-05": {
    "min": 10400.0,
    "max": 10600.0,
    "modal": 10500.0,
    "arrival": 1.2,
    "arrive_unit": "Tonnes",
    "price_unit": "Rs/Quintal",
    "variety": "Other"
  },
  "2014-08-12": {
    "min": 10300.0,
    "max": 10500.0,
    "modal": 10400.0,
    "arrival": 1.8,
    "arrive_unit": "Tonnes",
    "price_unit": "Rs/Quintal",
    "variety": "Other"
  }
}