{
  "2011-04-03": {
    "min": 1651.0,
    "max": 3101.0,
    "modal": 2600.0,
    "arrival": 11.0,
    "arrive_unit": "Tonnes",
    "price_unit": "Rs/Quintal",
    "variety": "Other"
  },
  "2011-04-10": {
    "min": 2000.0,
    "max": 3251.0,
    "modal": 2700.0,
    "arrival": 14.8,
    "arrive_unit": "Tonnes",
    "price_unit": "Rs/Quintal",
    "variety": "Other"
  },
  "2011-04-17": {
    "min": 2000.0,
    "max": 3310.0,
    "modal": 2751.0,
    "arrival": 17.5,
    "arrive_unit": "Tonnes",
    "price_unit": "Rs/Quintal",
    "variety": "Other"
  }
}