{
  "2012-04-07": {
    "min": 2935.0,
    "max": 3065.0,
    "modal": 3000.0,
    "arrival": 49.2,
    "arrive_unit": "Tonnes",
    "price_unit": "Rs/Quintal",
    "variety": "Other"
  },
  "2012-04-09": {
    "min": 2800.0,
    "max": 3115.0,
    "modal": 2958.0,
    "arrival": 37.5,
    "arrive_unit": "Tonnes",
    "price_unit": "Rs/Quintal",
    "variety": "Other"
  },
  "2012-04-10": {
    "min": 2900.0,
    "max": 3115.0,
    "modal": 3008.0,
    "arrival": 55.7,
    "arrive_unit": "Tonnes",
    "price_unit": "Rs/Quintal",
    "variety": "Other"
  },
  "2012-04-11": {
    "min": 2939.0,
    "max": 3110.0,
    "modal": 3025.0,
    "arrival": 40.0,
    "arrive_unit": "Tonnes",
    "price_unit": "Rs/Quintal",
    "variety": "Other"
  },
  "2012-04-12": {
    "min": 2800.0,
    "max": 3082.0,
    "modal": 2941.0,
    "arrival": 31.5,
    "arrive_unit": "Tonnes",
    "price_unit": "Rs/Quintal",
    "variety": "Other"
  },
  "2012-04-13": {
    "min": 2750.0,
    "max": 3091.0,
    "modal": 2921.0,
    "arrival": 25.3,
    "arrive_unit": "Tonnes",
    "price_unit": "Rs/Quintal",
    "variety": "Other"
  },
  "2012-04-16": {
    "min": 2875.0,
    "max": 3140.0,
    "modal": 3008.0,
    "arrival": 26.5,
    "arrive_unit": "Tonnes",
    "price_unit": "Rs/Quintal",
    "variety": "Other"
  },
  "2012-04-17": {
    "min": 2900.0,
    "max": 3158.0,
    "modal": 3029.0,
    "arrival": 38.1,
    "arrive_unit": "Tonnes",
    "price_unit": "Rs/Quintal",
    "variety": "Other"
  },
  "2012-04-18": {
    "min": 2909.0,
    "max": 3160.0,
    "modal": 3025.0,
    "arrival": 18.5,
    "arrive_unit": "Tonnes",
    "price_unit": "Rs/Quintal",
    "variety": "Other"
  },
  "2012-04-19": {
    "min": 2900.0,
    "max": 3150.0,
    "modal": 3025.0,
    "arrival": 21.6,
    "arrive_unit": "Tonnes",
    "price_unit": "Rs/Quintal",
    "variety": "Other"
  },
  "2012-04-20": {
    "min": 2960.0,
    "max": 3150.0,
    "modal": 3055.0,
    "arrival": 25.1,
    "arrive_unit": "Tonnes",
    "price_unit": "Rs/Quintal",
    "variety": "Other"
  },
  "2012-04-21": {
    "min": 2945.0,
    "max": 3160.0,
    "modal": 3053.0,
    "arrival": 35.1,
    "arrive_unit": "Tonnes",
    "price_unit": "Rs/Quintal",
    "variety": "Other"
  },
  "2012-04-23": {
    "min": 2849.0,
    "max": 3159.0,
    "modal": 3004.0,
    "arrival": 28.4,
    "arrive_unit": "Tonnes",
    "price_unit": "Rs/Quintal",
    "variety": "Other"
  },
  "2012-04-26": {
    "min": 2850.0,
    "max": 3052.0,
    "modal": 2951.0,
    "arrival": 21.5,
    "arrive_unit": "Tonnes",
    "price_unit": "Rs/Quintal",
    "variety": "Other"
  },
  "2012-04-30": {
    "min": 2800.0,
    "max": 3135.0,
    "modal": 2968.0,
    "arrival": 19.0,
    "arrive_unit": "Tonnes",
    "price_unit": "Rs/Quintal",
    "variety": "Other"
  }
}