{
  "2012-06-01": {
    "min": 1400.0,
    "max": 1651.0,
    "modal": 1500.0,
    "arrival": 7.8,
    "arrive_unit": "Tonnes",
    "price_unit": "Rs/Quintal",
    "variety": "Red"
  },
  "2012-06-02": {
    "min": 1430.0,
    "max": 1750.0,
    "modal": 1575.0,
    "arrival": 5.0,
    "arrive_unit": "Tonnes",
    "price_unit": "Rs/Quintal",
    "variety": "Red"
  },
  "2012-06-04": {
    "min": 1225.0,
    "max": 1625.0,
    "modal": 1500.0,
    "arrival": 9.3,
    "arrive_unit": "Tonnes",
    "price_unit": "Rs/Quintal",
    "variety": "Red"
  },
  "2012-06-05": {
    "min": 1300.0,
    "max": 1590.0,
    "modal": 1430.0,
    "arrival": 5.5,
    "arrive_unit": "Tonnes",
    "price_unit": "Rs/Quintal",
    "variety": "Red"
  },
  "2012-06-06": {
    "min": 1351.0,
    "max": 1775.0,
    "modal": 1500.0,
    "arrival": 2.5,
    "arrive_unit": "Tonnes",
    "price_unit": "Rs/Quintal",
    "variety": "Red"
  },
  "2012-06-07": {
    "min": 1250.0,
    "max": 1587.0,
    "modal": 1451.0,
    "arrival": 6.5,
    "arrive_unit": "Tonnes",
    "price_unit": "Rs/Quintal",
    "variety": "Red"
  },
  "2012-06-08": {
    "min": 1300.0,
    "max": 1651.0,
    "modal": 1430.0,
    "arrival": 9.5,
    "arrive_unit": "Tonnes",
    "price_unit": "Rs/Quintal",
    "variety": "Red"
  },
  "2012-06-09": {
    "min": 1321.0,
    "max": 1530.0,
    "modal": 1460.0,
    "arrival": 1.7,
    "arrive_unit": "Tonnes",
    "price_unit": "Rs/Quintal",
    "variety": "Red"
  },
  "2012-06-11": {
    "min": 1300.0,
    "max": 1650.0,
    "modal": 1500.0,
    "arrival": 6.45,
    "arrive_unit": "Tonnes",
    "price_unit": "Rs/Quintal",
    "variety": "Red"
  },
  "2012-06-12": {
    "min": 1201.0,
    "max": 1599.0,
    "modal": 1400.0,
    "arrival": 0.5,
    "arrive_unit": "Tonnes",
    "price_unit": "Rs/Quintal",
    "variety": "Red"
  },
  "2012-06-13": {
    "min": 1050.0,
    "max": 1569.0,
    "modal": 1425.0,
    "arrival": 0.1,
    "arrive_unit": "Tonnes",
    "price_unit": "Rs/Quintal",
    "variety": "Red"
  },
  "2012-06-14": {
    "min": 1200.0,
    "max": 1675.0,
    "modal": 1400.0,
    "arrival": 9.8,
    "arrive_unit": "Tonnes",
    "price_unit": "Rs/Quintal",
    "variety": "Red"
  },
  "2012-06-15": {
    "min": 1400.0,
    "max": 1570.0,
    "modal": 1500.0,
    "arrival": 0.5,
    "arrive_unit": "Tonnes",
    "price_unit": "Rs/Quintal",
    "variety": "Red"
  },
  "2012-06-16": {
    "min": 1300.0,
    "max": 1600.0,
    "modal": 1450.0,
    "arrival": 3.3,
    "arrive_unit": "Tonnes",
    "price_unit": "Rs/Quintal",
    "variety": "Red"
  },
  "2012-06-18": {
    "min": 1375.0,
    "max": 1551.0,
    "modal": 1475.0,
    "arrival": 6.8,
    "arrive_unit": "Tonnes",
    "price_unit": "Rs/Quintal",
    "variety": "Red"
  },
  "2012-06-20": {
    "min": 1375.0,
    "max": 1750.0,
    "modal": 1600.0,
    "arrival": 8.65,
    "arrive_unit": "Tonnes",
    "price_unit": "Rs/Quintal",
    "variety": "Red"
  },
  "2012-06-21": {
    "min": 1385.0,
    "max": 1800.0,
    "modal": 1500.0,
    "arrival": 5.7,
    "arrive_unit": "Tonnes",
    "price_unit": "Rs/Quintal",
    "variety": "Red"
  },
  "2012-06-22": {
    "min": 1486.0,
    "max": 1600.0,
    "modal": 1486.0,
    "arrival": 1.0,
    "arrive_unit": "Tonnes",
    "price_unit": "Rs/Quintal",
    "variety": "Red"
  },
  "2012-06-23": {
    "min": 1250.0,
    "max": 1801.0,
    "modal": 1551.0,
    "arrival": 6.5,
    "arrive_unit": "Tonnes",
    "price_unit": "Rs/Quintal",
    "variety": "Red"
  },
  "2012-06-25": {
    "min": 1346.0,
    "max": 1873.0,
    "modal": 1490.0,
    "arrival": 9.0,
    "arrive_unit": "Tonnes",
    "price_unit": "Rs/Quintal",
    "variety": "Red"
  },
  "2012-06-26": {
    "min": 1400.0,
    "max": 1801.0,
    "modal": 1600.0,
    "arrival": 4.5,
    "arrive_unit": "Tonnes",
    "price_unit": "Rs/Quintal",
    "variety": "Red"
  },
  "2012-06-27": {
    "min": 1200.0,
    "max": 1550.0,
    "modal": 1400.0,
    "arrival": 4.5,
    "arrive_unit": "Tonnes",
    "price_unit": "Rs/Quintal",
    "variety": "Red"
  },
  "2012-06-28": {
    "min": 1200.0,
    "max": 1800.0,
    "modal": 1500.0,
    "arrival": 9.2,
    "arrive_unit": "Tonnes",
    "price_unit": "Rs/Quintal",
    "variety": "Red"
  },
  "2012-06-29": {
    "min": 1525.0,
    "max": 1630.0,
    "modal": 1525.0,
    "arrival": 0.9,
    "arrive_unit": "Tonnes",
    "price_unit": "Rs/Quintal",
    "variety": "Red"
  }
}