{
  "2012-01-12": {
    "min": 4000.0,
    "max": 4000.0,
    "modal": 4000.0,
    "arrival": 21.5,
    "arrive_unit": "Tonnes",
    "price_unit": "Rs/Quintal",
    "variety": "Other"
  },
  "2012-01-13": {
    "min": 4000.0,
    "max": 4000.0,
    "modal": 4000.0,
    "arrival": 15.8,
    "arrive_unit": "Tonnes",
    "price_unit": "Rs/Quintal",
    "variety": "Other"
  },
  "2012-01-14": {
    "min": 4000.0,
    "max": 4000.0,
    "modal": 4000.0,
    "arrival": 19.2,
    "arrive_unit": "Tonnes",
    "price_unit": "Rs/Quintal",
    "variety": "Other"
  },
  "2012-01-16": {
    "min": 4000.0,
    "max": 4000.0,
    "modal": 4000.0,
    "arrival": 11.6,
    "arrive_unit": "Tonnes",
    "price_unit": "Rs/Quintal",
    "variety": "Other"
  },
  "2012-01-18": {
    "min": 4000.0,
    "max": 4000.0,
    "modal": 4000.0,
    "arrival": 49.0,
    "arrive_unit": "Tonnes",
    "price_unit": "Rs/Quintal",
    "variety": "Other"
  },
  "2012-01-19": {
    "min": 4000.0,
    "max": 4000.0,
    "modal": 4000.0,
    "arrival": 17.5,
    "arrive_unit": "Tonnes",
    "price_unit": "Rs/Quintal",
    "variety": "Other"
  },
  "2012-01-27": {
    "min": 3800.0,
    "max": 3900.0,
    "modal": 3850.0,
    "arrival": 27.2,
    "arrive_unit": "Tonnes",
    "price_unit": "Rs/Quintal",
    "variety": "Other"
  },
  "2012-01-28": {
    "min": 3800.0,
    "max": 3900.0,
    "modal": 3850.0,
    "arrival": 32.0,
    "arrive_unit": "Tonnes",
    "price_unit": "Rs/Quintal",
    "variety": "Other"
  }
}