{
  "2012-09-02": {
    "min": 1301.0,
    "max": 2051.0,
    "modal": 1600.0,
    "arrival": 0.4,
    "arrive_unit": "Tonnes",
    "price_unit": "Rs/Quintal",
    "variety": "Maharashtra 2189"
  },
  "2012-09-16": {
    "min": 1201.0,
    "max": 2052.0,
    "modal": 1919.0,
    "arrival": 1.2,
    "arrive_unit": "Tonnes",
    "price_unit": "Rs/Quintal",
    "variety": "Maharashtra 2189"
  },
  "2012-09-19": {
    "min": 1751.0,
    "max": 1951.0,
    "modal": 1760.0,
    "arrival": 0.8,
    "arrive_unit": "Tonnes",
    "price_unit": "Rs/Quintal",
    "variety": "Maharashtra 2189"
  },
  "2012-09-23": {
    "min": 1201.0,
    "max": 1700.0,
    "modal": 1325.0,
    "arrival": 0.6,
    "arrive_unit": "Tonnes",
    "price_unit": "Rs/Quintal",
    "variety": "Maharashtra 2189"
  },
  "2012-09-30": {
    "min": 1301.0,
    "max": 1500.0,
    "modal": 1400.0,
    "arrival": 0.4,
    "arrive_unit": "Tonnes",
    "price_unit": "Rs/Quintal",
    "variety": "Maharashtra 2189"
  }
}