{
  "2014-12-01": {
    "min": 1455.0,
    "max": 1675.0,
    "modal": 1565.0,
    "arrival": 5.7,
    "arrive_unit": "Tonnes",
    "price_unit": "Rs/Quintal",
    "variety": "Kalyan"
  },
  "2014-12-02": {
    "min": 1475.0,
    "max": 1575.0,
    "modal": 1525.0,
    "arrival": 5.1,
    "arrive_unit": "Tonnes",
    "price_unit": "Rs/Quintal",
    "variety": "Kalyan"
  },
  "2014-12-03": {
    "min": 1380.0,
    "max": 1625.0,
    "modal": 1505.0,
    "arrival": 6.0,
    "arrive_unit": "Tonnes",
    "price_unit": "Rs/Quintal",
    "variety": "Kalyan"
  },
  "2014-12-04": {
    "min": 1465.0,
    "max": 1600.0,
    "modal": 1535.0,
    "arrival": 6.3,
    "arrive_unit": "Tonnes",
    "price_unit": "Rs/Quintal",
    "variety": "Kalyan"
  },
  "2014-12-05": {
    "min": 1375.0,
    "max": 1600.0,
    "modal": 1490.0,
    "arrival": 7.5,
    "arrive_unit": "Tonnes",
    "price_unit": "Rs/Quintal",
    "variety": "Kalyan"
  },
  "2014-12-06": {
    "min": 1405.0,
    "max": 1650.0,
    "modal": 1530.0,
    "arrival": 6.0,
    "arrive_unit": "Tonnes",
    "price_unit": "Rs/Quintal",
    "variety": "Kalyan"
  },
  "2014-12-09": {
    "min": 1465.0,
    "max": 1600.0,
    "modal": 1535.0,
    "arrival": 6.0,
    "arrive_unit": "Tonnes",
    "price_unit": "Rs/Quintal",
    "variety": "Kalyan"
  },
  "2014-12-10": {
    "min": 1455.0,
    "max": 1610.0,
    "modal": 1535.0,
    "arrival": 5.4,
    "arrive_unit": "Tonnes",
    "price_unit": "Rs/Quintal",
    "variety": "Kalyan"
  },
  "2014-12-11": {
    "min": 1450.0,
    "max": 1635.0,
    "modal": 1545.0,
    "arrival": 3.54,
    "arrive_unit": "Tonnes",
    "price_unit": "Rs/Quintal",
    "variety": "Kalyan"
  },
  "2014-12-12": {
    "min": 1475.0,
    "max": 1635.0,
    "modal": 1555.0,
    "arrival": 6.3,
    "arrive_unit": "Tonnes",
    "price_unit": "Rs/Quintal",
    "variety": "Kalyan"
  },
  "2014-12-13": {
    "min": 1300.0,
    "max": 1630.0,
    "modal": 1465.0,
    "arrival": 4.2,
    "arrive_unit": "Tonnes",
    "price_unit": "Rs/Quintal",
    "variety": "Kalyan"
  },
  "2014-12-15": {
    "min": 1485.0,
    "max": 1780.0,
    "modal": 1635.0,
    "arrival": 3.3,
    "arrive_unit": "Tonnes",
    "price_unit": "Rs/Quintal",
    "variety": "Kalyan"
  },
  "2014-12-17": {
    "min": 1450.0,
    "max": 1730.0,
    "modal": 1590.0,
    "arrival": 3.48,
    "arrive_unit": "Tonnes",
    "price_unit": "Rs/Quintal",
    "variety": "Kalyan"
  },
  "2014-12-22": {
    "min": 1385.0,
    "max": 1630.0,
    "modal": 1510.0,
    "arrival": 2.88,
    "arrive_unit": "Tonnes",
    "price_unit": "Rs/Quintal",
    "variety": "Kalyan"
  },
  "2014-12-23": {
    "min": 1560.0,
    "max": 1640.0,
    "modal": 1600.0,
    "arrival": 5.46,
    "arrive_unit": "Tonnes",
    "price_unit": "Rs/Quintal",
    "variety": "Kalyan"
  },
  "2014-12-24": {
    "min": 1475.0,
    "max": 1615.0,
    "modal": 1545.0,
    "arrival": 2.4,
    "arrive_unit": "Tonnes",
    "price_unit": "Rs/Quintal",
    "variety": "Kalyan"
  },
  "2014-12-25": {
    "min": 1555.0,
    "max": 1705.0,
    "modal": 1630.0,
    "arrival": 2.04,
    "arrive_unit": "Tonnes",
    "price_unit": "Rs/Quintal",
    "variety": "Kalyan"
  },
  "2014-12-26": {
    "min": 1615.0,
    "max": 1770.0,
    "modal": 1695.0,
    "arrival": 2.1,
    "arrive_unit": "Tonnes",
    "price_unit": "Rs/Quintal",
    "variety": "Kalyan"
  },
  "2014-12-27": {
    "min": 1600.0,
    "max": 1835.0,
    "modal": 1720.0,
    "arrival": 3.0,
    "arrive_unit": "Tonnes",
    "price_unit": "Rs/Quintal",
    "variety": "Kalyan"
  },
  "2014-12-29": {
    "min": 1250.0,
    "max": 1850.0,
    "modal": 1550.0,
    "arrival": 3.06,
    "arrive_unit": "Tonnes",
    "price_unit": "Rs/Quintal",
    "variety": "Kalyan"
  },
  "2014-12-30": {
    "min": 1630.0,
    "max": 1930.0,
    "modal": 1780.0,
    "arrival": 4.2,
    "arrive_unit": "Tonnes",
    "price_unit": "Rs/Quintal",
    "variety": "Kalyan"
  },
  "2014-12-31": {
    "min": 1655.0,
    "max": 1940.0,
    "modal": 1800.0,
    "arrival": 2.4,
    "arrive_unit": "Tonnes",
    "price_unit": "Rs/Quintal",
    "variety": "Kalyan"
  }
}