{
  "2010-04-03": {
    "min": 3100.0,
    "max": 3350.0,
    "modal": 3245.0,
    "arrival": 108.79,
    "arrive_unit": "Tonnes",
    "price_unit": "Rs/Quintal",
    "variety": "Shanker 6 (B) 30mm FIne"
  },
  "2010-04-05": {
    "min": 3075.0,
    "max": 3350.0,
    "modal": 3221.0,
    "arrival": 69.88,
    "arrive_unit": "Tonnes",
    "price_unit": "Rs/Quintal",
    "variety": "Shanker 6 (B) 30mm FIne"
  },
  "2010-04-06": {
    "min": 3081.0,
    "max": 3350.0,
    "modal": 3221.0,
    "arrival": 111.32,
    "arrive_unit": "Tonnes",
    "price_unit": "Rs/Quintal",
    "variety": "Shanker 6 (B) 30mm FIne"
  },
  "2010-04-07": {
    "min": 3081.0,
    "max": 3350.0,
    "modal": 3221.0,
    "arrival": 70.75,
    "arrive_unit": "Tonnes",
    "price_unit": "Rs/Quintal",
    "variety": "Shanker 6 (B) 30mm FIne"
  },
  "2010-04-08": {
    "min": 3081.0,
    "max": 3350.0,
    "modal": 3221.0,
    "arrival": 53.43,
    "arrive_unit": "Tonnes",
    "price_unit": "Rs/Quintal",
    "variety": "Shanker 6 (B) 30mm FIne"
  },
  "2010-04-09": {
    "min": 3075.0,
    "max": 3311.0,
    "modal": 3175.0,
    "arrival": 98.58,
    "arrive_unit": "Tonnes",
    "price_unit": "Rs/Quintal",
    "variety": "Shanker 6 (B) 30mm FIne"
  },
  "2010-04-12": {
    "min": 3000.0,
    "max": 3250.0,
    "modal": 3135.0,
    "arrival": 46.93,
    "arrive_unit": "Tonnes",
    "price_unit": "Rs/Quintal",
    "variety": "Shanker 6 (B) 30mm FIne"
  },
  "2010-04-14": {
    "min": 3000.0,
    "max": 3250.0,
    "modal": 3150.0,
    "arrival": 138.09,
    "arrive_unit": "Tonnes",
    "price_unit": "Rs/Quintal",
    "variety": "Shanker 6 (B) 30mm FIne"
  },
  "2010-04-15": {
    "min": 3075.0,
    "max": 3250.0,
    "modal": 3151.0,
    "arrival": 82.62,
    "arrive_unit": "Tonnes",
    "price_unit": "Rs/Quintal",
    "variety": "Shanker 6 (B) 30mm FIne"
  },
  "2010-04-16": {
    "min": 3000.0,
    "max": 3250.0,
    "modal": 3105.0,
    "arrival": 102.21,
    "arrive_unit": "Tonnes",
    "price_unit": "Rs/Quintal",
    "variety": "Shanker 6 (B) 30mm FIne"
  },
  "2010-04-19": {
    "min": 3000.0,
    "max": 3200.0,
    "modal": 3100.0,
    "arrival": 85.66,
    "arrive_unit": "Tonnes",
    "price_unit": "Rs/Quintal",
    "variety": "Shanker 6 (B) 30mm FIne"
  },
  "2010-04-20": {
    "min": 3000.0,
    "max": 3200.0,
    "modal": 3100.0,
    "arrival": 49.68,
    "arrive_unit": "Tonnes",
    "price_unit": "Rs/Quintal",
    "variety": "Shanker 6 (B) 30mm FIne"
  },
  "2010-04-21": {
    "min": 3071.0,
    "max": 3175.0,
    "modal": 3100.0,
    "arrival": 92.85,
    "arrive_unit": "Tonnes",
    "price_unit": "Rs/Quintal",
    "variety": "Shanker 6 (B) 30mm FIne"
  },
  "2010-04-23": {
    "min": 3000.0,
    "max": 3175.0,
    "modal": 3100.0,
    "arrival": 88.03,
    "arrive_unit": "Tonnes",
    "price_unit": "Rs/Quintal",
    "variety": "Shanker 6 (B) 30mm FIne"
  },
  "2010-04-26": {
    "min": 2900.0,
    "max": 3100.0,
    "modal": 2975.0,
    "arrival": 88.88,
    "arrive_unit": "Tonnes",
    "price_unit": "Rs/Quintal",
    "variety": "Shanker 6 (B) 30mm FIne"
  },
  "2010-04-27": {
    "min": 2900.0,
    "max": 3100.0,
    "modal": 2975.0,
    "arrival": 98.42,
    "arrive_unit": "Tonnes",
    "price_unit": "Rs/Quintal",
    "variety": "Shanker 6 (B) 30mm FIne"
  },
  "2010-04-28": {
    "min": 2875.0,
    "max": 2951.0,
    "modal": 2900.0,
    "arrival": 57.72,
    "arrive_unit": "Tonnes",
    "price_unit": "Rs/Quintal",
    "variety": "Shanker 6 (B) 30mm FIne"
  },
  "2010-04-29": {
    "min": 2800.0,
    "max": 3100.0,
    "modal": 2900.0,
    "arrival": 94.74,
    "arrive_unit": "Tonnes",
    "price_unit": "Rs/Quintal",
    "variety": "Shanker 6 (B) 30mm FIne"
  },
  "2010-04-30": {
    "min": 2700.0,
    "max": 3100.0,
    "modal": 2900.0,
    "arrival": 35.87,
    "arrive_unit": "Tonnes",
    "price_unit": "Rs/Quintal",
    "variety": "Shanker 6 (B) 30mm FIne"
  }
}