{
  "2012-12-03": {
    "min": 1811.0,
    "max": 6289.0,
    "modal": 4989.0,
    "arrival": 52.0,
    "arrive_unit": "Tonnes",
    "price_unit": "Rs/Quintal",
    "variety": "Gejje"
  },
  "2012-12-04": {
    "min": 2019.0,
    "max": 6239.0,
    "modal": 4461.0,
    "arrival": 8.0,
    "arrive_unit": "Tonnes",
    "price_unit": "Rs/Quintal",
    "variety": "Gejje"
  },
  "2012-12-05": {
    "min": 1889.0,
    "max": 5989.0,
    "modal": 4639.0,
    "arrival": 4.0,
    "arrive_unit": "Tonnes",
    "price_unit": "Rs/Quintal",
    "variety": "Gejje"
  },
  "2012-12-06": {
    "min": 1919.0,
    "max": 6189.0,
    "modal": 5139.0,
    "arrival": 9.0,
    "arrive_unit": "Tonnes",
    "price_unit": "Rs/Quintal",
    "variety": "Gejje"
  },
  "2012-12-07": {
    "min": 2096.0,
    "max": 6269.0,
    "modal": 5219.0,
    "arrival": 77.0,
    "arrive_unit": "Tonnes",
    "price_unit": "Rs/Quintal",
    "variety": "Gejje"
  },
  "2012-12-08": {
    "min": 3038.0,
    "max": 5889.0,
    "modal": 5191.0,
    "arrival": 5.0,
    "arrive_unit": "Tonnes",
    "price_unit": "Rs/Quintal",
    "variety": "Gejje"
  },
  "2012-12-10": {
    "min": 2688.0,
    "max": 6227.0,
    "modal": 4825.0,
    "arrival": 34.5,
    "arrive_unit": "Tonnes",
    "price_unit": "Rs/Quintal",
    "variety": "Gejje"
  },
  "2012-12-11": {
    "min": 3765.0,
    "max": 6169.0,
    "modal": 4489.0,
    "arrival": 6.0,
    "arrive_unit": "Tonnes",
    "price_unit": "Rs/Quintal",
    "variety": "Gejje"
  },
  "2012-12-12": {
    "min": 2509.0,
    "max": 6153.0,
    "modal": 4943.0,
    "arrival": 8.0,
    "arrive_unit": "Tonnes",
    "price_unit": "Rs/Quintal",
    "variety": "Gejje"
  },
  "2012-12-14": {
    "min": 2409.0,
    "max": 6214.0,
    "modal": 4843.0,
    "arrival": 40.5,
    "arrive_unit": "Tonnes",
    "price_unit": "Rs/Quintal",
    "variety": "Gejje"
  },
  "2012-12-15": {
    "min": 2419.0,
    "max": 5837.0,
    "modal": 4469.0,
    "arrival": 9.0,
    "arrive_unit": "Tonnes",
    "price_unit": "Rs/Quintal",
    "variety": "Gejje"
  },
  "2012-12-17": {
    "min": 2189.0,
    "max": 6209.0,
    "modal": 5119.0,
    "arrival": 49.5,
    "arrive_unit": "Tonnes",
    "price_unit": "Rs/Quintal",
    "variety": "Gejje"
  },
  "2012-12-18": {
    "min": 2859.0,
    "max": 5729.0,
    "modal": 4809.0,
    "arrival": 21.0,
    "arrive_unit": "Tonnes",
    "price_unit": "Rs/Quintal",
    "variety": "Gejje"
  },
  "2012-12-19": {
    "min": 2448.0,
    "max": 5600.0,
    "modal": 3389.0,
    "arrival": 17.0,
    "arrive_unit": "Tonnes",
    "price_unit": "Rs/Quintal",
    "variety": "Gejje"
  },
  "2012-12-20": {
    "min": 2619.0,
    "max": 5560.0,
    "modal": 4555.0,
    "arrival": 19.0,
    "arrive_unit": "Tonnes",
    "price_unit": "Rs/Quintal",
    "variety": "Gejje"
  },
  "2012-12-21": {
    "min": 1584.0,
    "max": 6059.0,
    "modal": 4439.0,
    "arrival": 62.0,
    "arrive_unit": "Tonnes",
    "price_unit": "Rs/Quintal",
    "variety": "Gejje"
  },
  "2012-12-22": {
    "min": 2028.0,
    "max": 5319.0,
    "modal": 4469.0,
    "arrival": 6.5,
    "arrive_unit": "Tonnes",
    "price_unit": "Rs/Quintal",
    "variety": "Gejje"
  },
  "2012-12-24": {
    "min": 2048.0,
    "max": 5969.0,
    "modal": 4369.0,
    "arrival": 67.0,
    "arrive_unit": "Tonnes",
    "price_unit": "Rs/Quintal",
    "variety": "Gejje"
  },
  "2012-12-26": {
    "min": 3361.0,
    "max": 5749.0,
    "modal": 4509.0,
    "arrival": 16.5,
    "arrive_unit": "Tonnes",
    "price_unit": "Rs/Quintal",
    "variety": "Gejje"
  },
  "2012-12-27": {
    "min": 2608.0,
    "max": 5889.0,
    "modal": 4636.0,
    "arrival": 30.0,
    "arrive_unit": "Tonnes",
    "price_unit": "Rs/Quintal",
    "variety": "Gejje"
  },
  "2012-12-28": {
    "min": 2662.0,
    "max": 5295.0,
    "modal": 4109.0,
    "arrival": 103.0,
    "arrive_unit": "Tonnes",
    "price_unit": "Rs/Quintal",
    "variety": "Balli/Habbu"
  },
  "2012-12-29": {
    "min": 2679.0,
    "max": 5091.0,
    "modal": 4309.0,
    "arrival": 16.0,
    "arrive_unit": "Tonnes",
    "price_unit": "Rs/Quintal",
    "variety": "Balli/Habbu"
  },
  "2012-12-31": {
    "min": 3219.0,
    "max": 6009.0,
    "modal": 5248.0,
    "arrival": 45.0,
    "arrive_unit": "Tonnes",
    "price_unit": "Rs/Quintal",
    "variety": "Gejje"
  }
}