{
  "2012-01-01": {
    "min": 1100.0,
    "max": 1450.0,
    "modal": 1275.0,
    "arrival": 83.5,
    "arrive_unit": "Tonnes",
    "price_unit": "Rs/Quintal",
    "variety": "Paddy fine"
  },
  "2012-01-03": {
    "min": 1100.0,
    "max": 1350.0,
    "modal": 1225.0,
    "arrival": 159.0,
    "arrive_unit": "Tonnes",
    "price_unit": "Rs/Quintal",
    "variety": "Paddy fine"
  },
  "2012-01-05": {
    "min": 1100.0,
    "max": 1360.0,
    "modal": 1230.0,
    "arrival": 161.5,
    "arrive_unit": "Tonnes",
    "price_unit": "Rs/Quintal",
    "variety": "Paddy fine"
  },
  "2012-01-07": {
    "min": 1100.0,
    "max": 1350.0,
    "modal": 1325.0,
    "arrival": 178.5,
    "arrive_unit": "Tonnes",
    "price_unit": "Rs/Quintal",
    "variety": "Paddy fine"
  },
  "2012-01-08": {
    "min": 1100.0,
    "max": 1370.0,
    "modal": 1235.0,
    "arrival": 172.5,
    "arrive_unit": "Tonnes",
    "price_unit": "Rs/Quintal",
    "variety": "Paddy fine"
  },
  "2012-01-09": {
    "min": 1100.0,
    "max": 1400.0,
    "modal": 1250.0,
    "arrival": 123.5,
    "arrive_unit": "Tonnes",
    "price_unit": "Rs/Quintal",
    "variety": "Paddy fine"
  },
  "2012-01-11": {
    "min": 1100.0,
    "max": 1360.0,
    "modal": 1230.0,
    "arrival": 135.0,
    "arrive_unit": "Tonnes",
    "price_unit": "Rs/Quintal",
    "variety": "Paddy fine"
  },
  "2012-01-13": {
    "min": 1100.0,
    "max": 1370.0,
    "modal": 1235.0,
    "arrival": 169.0,
    "arrive_unit": "Tonnes",
    "price_unit": "Rs/Quintal",
    "variety": "Paddy fine"
  }
}