{
  "2014-05-01": {
    "min": 1351.0,
    "max": 1566.0,
    "modal": 1450.0,
    "arrival": 71.08,
    "arrive_unit": "Tonnes",
    "price_unit": "Rs/Quintal",
    "variety": "Lokwan"
  },
  "2014-05-05": {
    "min": 1175.0,
    "max": 1440.0,
    "modal": 1350.0,
    "arrival": 90.0,
    "arrive_unit": "Tonnes",
    "price_unit": "Rs/Quintal",
    "variety": "Lokwan"
  },
  "2014-05-06": {
    "min": 1279.0,
    "max": 1550.0,
    "modal": 1419.0,
    "arrival": 71.08,
    "arrive_unit": "Tonnes",
    "price_unit": "Rs/Quintal",
    "variety": "Lokwan"
  },
  "2014-05-07": {
    "min": 1375.0,
    "max": 1460.0,
    "modal": 1414.0,
    "arrival": 72.02,
    "arrive_unit": "Tonnes",
    "price_unit": "Rs/Quintal",
    "variety": "Lokwan"
  },
  "2014-05-08": {
    "min": 1440.0,
    "max": 1550.0,
    "modal": 1485.0,
    "arrival": 60.09,
    "arrive_unit": "Tonnes",
    "price_unit": "Rs/Quintal",
    "variety": "Lokwan"
  },
  "2014-05-09": {
    "min": 1386.0,
    "max": 1510.0,
    "modal": 1441.0,
    "arrival": 45.0,
    "arrive_unit": "Tonnes",
    "price_unit": "Rs/Quintal",
    "variety": "Lokwan"
  },
  "2014-05-12": {
    "min": 1356.0,
    "max": 1555.0,
    "modal": 1425.0,
    "arrival": 31.08,
    "arrive_unit": "Tonnes",
    "price_unit": "Rs/Quintal",
    "variety": "Lokwan"
  },
  "2014-05-13": {
    "min": 1389.0,
    "max": 1460.0,
    "modal": 1440.0,
    "arrival": 27.02,
    "arrive_unit": "Tonnes",
    "price_unit": "Rs/Quintal",
    "variety": "Lokwan"
  },
  "2014-05-14": {
    "min": 1351.0,
    "max": 1464.0,
    "modal": 1400.0,
    "arrival": 14.06,
    "arrive_unit": "Tonnes",
    "price_unit": "Rs/Quintal",
    "variety": "Lokwan"
  },
  "2014-05-15": {
    "min": 1389.0,
    "max": 1460.0,
    "modal": 1440.0,
    "arrival": 27.02,
    "arrive_unit": "Tonnes",
    "price_unit": "Rs/Quintal",
    "variety": "Lokwan"
  },
  "2014-05-16": {
    "min": 1380.0,
    "max": 1494.0,
    "modal": 1400.0,
    "arrival": 49.0,
    "arrive_unit": "Tonnes",
    "price_unit": "Rs/Quintal",
    "variety": "Lokwan"
  },
  "2014-05-19": {
    "min": 1396.0,
    "max": 1711.0,
    "modal": 1451.0,
    "arrival": 33.09,
    "arrive_unit": "Tonnes",
    "price_unit": "Rs/Quintal",
    "variety": "Lokwan"
  },
  "2014-05-20": {
    "min": 1414.0,
    "max": 1550.0,
    "modal": 1441.0,
    "arrival": 26.02,
    "arrive_unit": "Tonnes",
    "price_unit": "Rs/Quintal",
    "variety": "Lokwan"
  },
  "2014-05-21": {
    "min": 1405.0,
    "max": 1461.0,
    "modal": 1450.0,
    "arrival": 14.03,
    "arrive_unit": "Tonnes",
    "price_unit": "Rs/Quintal",
    "variety": "Lokwan"
  },
  "2014-05-22": {
    "min": 1399.0,
    "max": 1501.0,
    "modal": 1450.0,
    "arrival": 42.06,
    "arrive_unit": "Tonnes",
    "price_unit": "Rs/Quintal",
    "variety": "Lokwan"
  },
  "2014-05-23": {
    "min": 1300.0,
    "max": 1460.0,
    "modal": 1400.0,
    "arrival": 41.01,
    "arrive_unit": "Tonnes",
    "price_unit": "Rs/Quintal",
    "variety": "Lokwan"
  },
  "2014-05-26": {
    "min": 1300.0,
    "max": 1400.0,
    "modal": 1362.0,
    "arrival": 43.03,
    "arrive_unit": "Tonnes",
    "price_unit": "Rs/Quintal",
    "variety": "Lokwan"
  },
  "2014-05-27": {
    "min": 1252.0,
    "max": 1360.0,
    "modal": 1300.0,
    "arrival": 26.09,
    "arrive_unit": "Tonnes",
    "price_unit": "Rs/Quintal",
    "variety": "Lokwan"
  },
  "2014-05-28": {
    "min": 1352.0,
    "max": 1401.0,
    "modal": 1388.0,
    "arrival": 14.01,
    "arrive_unit": "Tonnes",
    "price_unit": "Rs/Quintal",
    "variety": "Lokwan"
  },
  "2014-05-29": {
    "min": 1341.0,
    "max": 1431.0,
    "modal": 1401.0,
    "arrival": 25.02,
    "arrive_unit": "Tonnes",
    "price_unit": "Rs/Quintal",
    "variety": "Lokwan"
  },
  "2014-05-30": {
    "min": 1250.0,
    "max": 1486.0,
    "modal": 1355.0,
    "arrival": 9.0,
    "arrive_unit": "Tonnes",
    "price_unit": "Rs/Quintal",
    "variety": "Lokwan"
  }
}