{
  "2011-06-05": {
    "min": 150.0,
    "max": 180.0,
    "modal": 180.0,
    "arrival": 4.3,
    "arrive_unit": "Tonnes",
    "price_unit": "Rs/Quintal",
    "variety": "Bottle Gourd"
  },
  "2011-06-06": {
    "min": 120.0,
    "max": 150.0,
    "modal": 130.0,
    "arrival": 3.8,
    "arrive_unit": "Tonnes",
    "price_unit": "Rs/Quintal",
    "variety": "Bottle Gourd"
  },
  "2011-06-12": {
    "min": 150.0,
    "max": 200.0,
    "modal": 158.0,
    "arrival": 3.2,
    "arrive_unit": "Tonnes",
    "price_unit": "Rs/Quintal",
    "variety": "Bottle Gourd"
  },
  "2011-06-14": {
    "min": 100.0,
    "max": 150.0,
    "modal": 126.0,
    "arrival": 1.5,
    "arrive_unit": "Tonnes",
    "price_unit": "Rs/Quintal",
    "variety": "Bottle Gourd"
  },
  "2011-06-18": {
    "min": 150.0,
    "max": 160.0,
    "modal": 160.0,
    "arrival": 7.0,
    "arrive_unit": "Tonnes",
    "price_unit": "Rs/Quintal",
    "variety": "Bottle Gourd"
  },
  "2011-06-24": {
    "min": 190.0,
    "max": 200.0,
    "modal": 200.0,
    "arrival": 2.3,
    "arrive_unit": "Tonnes",
    "price_unit": "Rs/Quintal",
    "variety": "Bottle Gourd"
  }
}