{
  "2012-05-02": {
    "min": 3112.0,
    "max": 6320.0,
    "modal": 3700.0,
    "arrival": 787.3,
    "arrive_unit": "Tonnes",
    "price_unit": "Rs/Quintal",
    "variety": "Other"
  },
  "2012-05-04": {
    "min": 3165.0,
    "max": 6800.0,
    "modal": 3900.0,
    "arrival": 45.09,
    "arrive_unit": "Tonnes",
    "price_unit": "Rs/Quintal",
    "variety": "Other"
  },
  "2012-05-05": {
    "min": 3040.0,
    "max": 7000.0,
    "modal": 3800.0,
    "arrival": 70.5,
    "arrive_unit": "Tonnes",
    "price_unit": "Rs/Quintal",
    "variety": "Other"
  },
  "2012-05-07": {
    "min": 3240.0,
    "max": 6600.0,
    "modal": 4000.0,
    "arrival": 71.83,
    "arrive_unit": "Tonnes",
    "price_unit": "Rs/Quintal",
    "variety": "Other"
  },
  "2012-05-08": {
    "min": 3318.0,
    "max": 7200.0,
    "modal": 3950.0,
    "arrival": 82.78,
    "arrive_unit": "Tonnes",
    "price_unit": "Rs/Quintal",
    "variety": "Other"
  },
  "2012-05-09": {
    "min": 3016.0,
    "max": 7140.0,
    "modal": 3960.0,
    "arrival": 86.19,
    "arrive_unit": "Tonnes",
    "price_unit": "Rs/Quintal",
    "variety": "Other"
  },
  "2012-05-11": {
    "min": 3318.0,
    "max": 7036.0,
    "modal": 4086.0,
    "arrival": 37.65,
    "arrive_unit": "Tonnes",
    "price_unit": "Rs/Quintal",
    "variety": "Other"
  },
  "2012-05-12": {
    "min": 3330.0,
    "max": 7186.0,
    "modal": 4851.0,
    "arrival": 37.83,
    "arrive_unit": "Tonnes",
    "price_unit": "Rs/Quintal",
    "variety": "Other"
  },
  "2012-05-13": {
    "min": 3416.0,
    "max": 7058.0,
    "modal": 4066.0,
    "arrival": 55.72,
    "arrive_unit": "Tonnes",
    "price_unit": "Rs/Quintal",
    "variety": "Other"
  },
  "2012-05-14": {
    "min": 3212.0,
    "max": 7012.0,
    "modal": 4086.0,
    "arrival": 32.25,
    "arrive_unit": "Tonnes",
    "price_unit": "Rs/Quintal",
    "variety": "Other"
  },
  "2012-05-15": {
    "min": 3216.0,
    "max": 6980.0,
    "modal": 4100.0,
    "arrival": 40.6,
    "arrive_unit": "Tonnes",
    "price_unit": "Rs/Quintal",
    "variety": "Other"
  },
  "2012-05-16": {
    "min": 3312.0,
    "max": 7065.0,
    "modal": 4005.0,
    "arrival": 44.44,
    "arrive_unit": "Tonnes",
    "price_unit": "Rs/Quintal",
    "variety": "Other"
  },
  "2012-05-18": {
    "min": 2612.0,
    "max": 6996.0,
    "modal": 3975.0,
    "arrival": 27.32,
    "arrive_unit": "Tonnes",
    "price_unit": "Rs/Quintal",
    "variety": "Other"
  },
  "2012-05-19": {
    "min": 3180.0,
    "max": 6870.0,
    "modal": 4025.0,
    "arrival": 22.98,
    "arrive_unit": "Tonnes",
    "price_unit": "Rs/Quintal",
    "variety": "Other"
  },
  "2012-05-21": {
    "min": 3216.0,
    "max": 6618.0,
    "modal": 4015.0,
    "arrival": 43.13,
    "arrive_unit": "Tonnes",
    "price_unit": "Rs/Quintal",
    "variety": "Other"
  },
  "2012-05-22": {
    "min": 3202.0,
    "max": 6815.0,
    "modal": 3980.0,
    "arrival": 24.57,
    "arrive_unit": "Tonnes",
    "price_unit": "Rs/Quintal",
    "variety": "Other"
  },
  "2012-05-23": {
    "min": 2912.0,
    "max": 7012.0,
    "modal": 3995.0,
    "arrival": 24.8,
    "arrive_unit": "Tonnes",
    "price_unit": "Rs/Quintal",
    "variety": "Other"
  },
  "2012-05-25": {
    "min": 2804.0,
    "max": 7068.0,
    "modal": 3990.0,
    "arrival": 19.8,
    "arrive_unit": "Tonnes",
    "price_unit": "Rs/Quintal",
    "variety": "Other"
  },
  "2012-05-26": {
    "min": 2706.0,
    "max": 6915.0,
    "modal": 4000.0,
    "arrival": 16.7,
    "arrive_unit": "Tonnes",
    "price_unit": "Rs/Quintal",
    "variety": "Other"
  },
  "2012-05-27": {
    "min": 2666.0,
    "max": 6816.0,
    "modal": 3970.0,
    "arrival": 22.94,
    "arrive_unit": "Tonnes",
    "price_unit": "Rs/Quintal",
    "variety": "Other"
  },
  "2012-05-28": {
    "min": 3012.0,
    "max": 6514.0,
    "modal": 3975.0,
    "arrival": 17.05,
    "arrive_unit": "Tonnes",
    "price_unit": "Rs/Quintal",
    "variety": "Other"
  },
  "2012-05-29": {
    "min": 2986.0,
    "max": 6312.0,
    "modal": 3960.0,
    "arrival": 17.36,
    "arrive_unit": "Tonnes",
    "price_unit": "Rs/Quintal",
    "variety": "Other"
  }
}