{
  "2015-07-27": {
    "min": 1400.0,
    "max": 1400.0,
    "modal": 1400.0,
    "arrival": 10.0,
    "arrive_unit": "Tonnes",
    "price_unit": "Rs/Quintal",
    "variety": "Other"
  },
  "2015-07-28": {
    "min": 1400.0,
    "max": 1400.0,
    "modal": 1400.0,
    "arrival": 8.0,
    "arrive_unit": "Tonnes",
    "price_unit": "Rs/Quintal",
    "variety": "Other"
  },
  "2015-07-29": {
    "min": 1400.0,
    "max": 1400.0,
    "modal": 1400.0,
    "arrival": 9.2,
    "arrive_unit": "Tonnes",
    "price_unit": "Rs/Quintal",
    "variety": "Other"
  },
  "2015-07-31": {
    "min": 1400.0,
    "max": 1400.0,
    "modal": 1400.0,
    "arrival": 3.0,
    "arrive_unit": "Tonnes",
    "price_unit": "Rs/Quintal",
    "variety": "Other"
  }
}