{
  "2014-10-11": {
    "min": 3210.0,
    "max": 3210.0,
    "modal": 3210.0,
    "arrival": 0.2,
    "arrive_unit": "Tonnes",
    "price_unit": "Rs/Quintal",
    "variety": "Other"
  },
  "2014-10-16": {
    "min": 3000.0,
    "max": 3000.0,
    "modal": 3000.0,
    "arrival": 0.1,
    "arrive_unit": "Tonnes",
    "price_unit": "Rs/Quintal",
    "variety": "Other"
  },
  "2014-10-17": {
    "min": 3115.0,
    "max": 3115.0,
    "modal": 3115.0,
    "arrival": 0.2,
    "arrive_unit": "Tonnes",
    "price_unit": "Rs/Quintal",
    "variety": "Other"
  },
  "2014-10-18": {
    "min": 3010.0,
    "max": 3010.0,
    "modal": 3010.0,
    "arrival": 0.4,
    "arrive_unit": "Tonnes",
    "price_unit": "Rs/Quintal",
    "variety": "Other"
  },
  "2014-10-27": {
    "min": 2960.0,
    "max": 3300.0,
    "modal": 3131.0,
    "arrival": 0.7,
    "arrive_unit": "Tonnes",
    "price_unit": "Rs/Quintal",
    "variety": "Other"
  },
  "2014-10-28": {
    "min": 1720.0,
    "max": 3660.0,
    "modal": 3100.0,
    "arrival": 1.2,
    "arrive_unit": "Tonnes",
    "price_unit": "Rs/Quintal",
    "variety": "Other"
  },
  "2014-10-29": {
    "min": 2980.0,
    "max": 3091.0,
    "modal": 3080.0,
    "arrival": 0.3,
    "arrive_unit": "Tonnes",
    "price_unit": "Rs/Quintal",
    "variety": "Other"
  },
  "2014-10-30": {
    "min": 2090.0,
    "max": 2090.0,
    "modal": 2090.0,
    "arrival": 0.1,
    "arrive_unit": "Tonnes",
    "price_unit": "Rs/Quintal",
    "variety": "Other"
  },
  "2014-10-31": {
    "min": 2390.0,
    "max": 3161.0,
    "modal": 2790.0,
    "arrival": 1.8,
    "arrive_unit": "Tonnes",
    "price_unit": "Rs/Quintal",
    "variety": "Other"
  }
}