{
  "2015-05-05": {
    "min": 1006.0,
    "max": 1680.0,
    "modal": 1256.0,
    "arrival": 4.0,
    "arrive_unit": "Tonnes",
    "price_unit": "Rs/Quintal",
    "variety": "Jowar ( White)"
  },
  "2015-05-06": {
    "min": 1062.0,
    "max": 1279.0,
    "modal": 1226.0,
    "arrival": 2.0,
    "arrive_unit": "Tonnes",
    "price_unit": "Rs/Quintal",
    "variety": "Jowar ( White)"
  },
  "2015-05-07": {
    "min": 1026.0,
    "max": 1675.0,
    "modal": 1305.0,
    "arrival": 11.0,
    "arrive_unit": "Tonnes",
    "price_unit": "Rs/Quintal",
    "variety": "Jowar ( White)"
  },
  "2015-05-08": {
    "min": 1416.0,
    "max": 1416.0,
    "modal": 1416.0,
    "arrival": 3.0,
    "arrive_unit": "Tonnes",
    "price_unit": "Rs/Quintal",
    "variety": "Jowar ( White)"
  },
  "2015-05-09": {
    "min": 1006.0,
    "max": 1719.0,
    "modal": 1509.0,
    "arrival": 18.0,
    "arrive_unit": "Tonnes",
    "price_unit": "Rs/Quintal",
    "variety": "Jowar ( White)"
  },
  "2015-05-11": {
    "min": 1061.0,
    "max": 1686.0,
    "modal": 1276.0,
    "arrival": 11.0,
    "arrive_unit": "Tonnes",
    "price_unit": "Rs/Quintal",
    "variety": "Jowar ( White)"
  },
  "2015-05-12": {
    "min": 1071.0,
    "max": 2026.0,
    "modal": 1601.0,
    "arrival": 4.0,
    "arrive_unit": "Tonnes",
    "price_unit": "Rs/Quintal",
    "variety": "Jowar ( White)"
  },
  "2015-05-14": {
    "min": 1062.0,
    "max": 1576.0,
    "modal": 1329.0,
    "arrival": 11.0,
    "arrive_unit": "Tonnes",
    "price_unit": "Rs/Quintal",
    "variety": "Jowar ( White)"
  },
  "2015-05-15": {
    "min": 1326.0,
    "max": 1326.0,
    "modal": 1326.0,
    "arrival": 1.0,
    "arrive_unit": "Tonnes",
    "price_unit": "Rs/Quintal",
    "variety": "Jowar ( White)"
  },
  "2015-05-16": {
    "min": 1078.0,
    "max": 2076.0,
    "modal": 1526.0,
    "arrival": 17.0,
    "arrive_unit": "Tonnes",
    "price_unit": "Rs/Quintal",
    "variety": "Jowar ( White)"
  },
  "2015-05-19": {
    "min": 1011.0,
    "max": 1489.0,
    "modal": 1406.0,
    "arrival": 4.0,
    "arrive_unit": "Tonnes",
    "price_unit": "Rs/Quintal",
    "variety": "Jowar ( White)"
  },
  "2015-05-20": {
    "min": 1106.0,
    "max": 2119.0,
    "modal": 1616.0,
    "arrival": 2.0,
    "arrive_unit": "Tonnes",
    "price_unit": "Rs/Quintal",
    "variety": "Jowar Hybrid"
  },
  "2015-05-21": {
    "min": 1080.0,
    "max": 1516.0,
    "modal": 1356.0,
    "arrival": 19.0,
    "arrive_unit": "Tonnes",
    "price_unit": "Rs/Quintal",
    "variety": "Jowar ( White)"
  },
  "2015-05-22": {
    "min": 1086.0,
    "max": 1726.0,
    "modal": 1376.0,
    "arrival": 4.0,
    "arrive_unit": "Tonnes",
    "price_unit": "Rs/Quintal",
    "variety": "Jowar ( White)"
  },
  "2015-05-23": {
    "min": 1101.0,
    "max": 1545.0,
    "modal": 1216.0,
    "arrival": 9.0,
    "arrive_unit": "Tonnes",
    "price_unit": "Rs/Quintal",
    "variety": "Jowar ( White)"
  },
  "2015-05-25": {
    "min": 1086.0,
    "max": 1766.0,
    "modal": 1476.0,
    "arrival": 10.0,
    "arrive_unit": "Tonnes",
    "price_unit": "Rs/Quintal",
    "variety": "Jowar ( White)"
  },
  "2015-05-28": {
    "min": 1086.0,
    "max": 1826.0,
    "modal": 1426.0,
    "arrival": 14.0,
    "arrive_unit": "Tonnes",
    "price_unit": "Rs/Quintal",
    "variety": "Jowar ( White)"
  },
  "2015-05-29": {
    "min": 1116.0,
    "max": 1286.0,
    "modal": 1226.0,
    "arrival": 2.0,
    "arrive_unit": "Tonnes",
    "price_unit": "Rs/Quintal",
    "variety": "Jowar ( White)"
  },
  "2015-05-30": {
    "min": 1006.0,
    "max": 1716.0,
    "modal": 1276.0,
    "arrival": 13.0,
    "arrive_unit": "Tonnes",
    "price_unit": "Rs/Quintal",
    "variety": "Jowar ( White)"
  }
}