{
  "2012-01-04": {
    "min": 400.0,
    "max": 500.0,
    "modal": 450.0,
    "arrival": 30.5,
    "arrive_unit": "Tonnes",
    "price_unit": "Rs/Quintal",
    "variety": "Other"
  },
  "2012-01-05": {
    "min": 400.0,
    "max": 500.0,
    "modal": 450.0,
    "arrival": 27.0,
    "arrive_unit": "Tonnes",
    "price_unit": "Rs/Quintal",
    "variety": "Other"
  },
  "2012-01-23": {
    "min": 650.0,
    "max": 650.0,
    "modal": 650.0,
    "arrival": 1.0,
    "arrive_unit": "Tonnes",
    "price_unit": "Rs/Quintal",
    "variety": "Local"
  }
}