{
  "2015-01-06": {
    "min": 64269.0,
    "max": 64269.0,
    "modal": 64269.0,
    "arrival": 1.0,
    "arrive_unit": "Tonnes",
    "price_unit": "Rs/Quintal",
    "variety": "Other"
  },
  "2015-01-09": {
    "min": 63609.0,
    "max": 63609.0,
    "modal": 63609.0,
    "arrival": 1.0,
    "arrive_unit": "Tonnes",
    "price_unit": "Rs/Quintal",
    "variety": "Other"
  },
  "2015-01-30": {
    "min": 62189.0,
    "max": 62389.0,
    "modal": 62189.0,
    "arrival": 1.0,
    "arrive_unit": "Tonnes",
    "price_unit": "Rs/Quintal",
    "variety": "Other"
  }
}