{
  "2010-10-01": {
    "min": 3700.0,
    "max": 4300.0,
    "modal": 4100.0,
    "arrival": 1.0,
    "arrive_unit": "Tonnes",
    "price_unit": "Rs/Quintal",
    "variety": "MCU 5"
  },
  "2010-10-02": {
    "min": 4000.0,
    "max": 4200.0,
    "modal": 4100.0,
    "arrival": 1.0,
    "arrive_unit": "Tonnes",
    "price_unit": "Rs/Quintal",
    "variety": "MCU 5"
  },
  "2010-10-03": {
    "min": 3900.0,
    "max": 4200.0,
    "modal": 4000.0,
    "arrival": 1.0,
    "arrive_unit": "Tonnes",
    "price_unit": "Rs/Quintal",
    "variety": "MCU 5"
  },
  "2010-10-04": {
    "min": 4000.0,
    "max": 4200.0,
    "modal": 4100.0,
    "arrival": 1.0,
    "arrive_unit": "Tonnes",
    "price_unit": "Rs/Quintal",
    "variety": "MCU 5"
  },
  "2010-10-05": {
    "min": 3900.0,
    "max": 4200.0,
    "modal": 4000.0,
    "arrival": 1.0,
    "arrive_unit": "Tonnes",
    "price_unit": "Rs/Quintal",
    "variety": "MCU 5"
  },
  "2010-10-06": {
    "min": 4000.0,
    "max": 4300.0,
    "modal": 4100.0,
    "arrival": 1.0,
    "arrive_unit": "Tonnes",
    "price_unit": "Rs/Quintal",
    "variety": "MCU 5"
  },
  "2010-10-07": {
    "min": 4000.0,
    "max": 4200.0,
    "modal": 4100.0,
    "arrival": 1.0,
    "arrive_unit": "Tonnes",
    "price_unit": "Rs/Quintal",
    "variety": "MCU 5"
  },
  "2010-10-08": {
    "min": 4000.0,
    "max": 4200.0,
    "modal": 4100.0,
    "arrival": 1.0,
    "arrive_unit": "Tonnes",
    "price_unit": "Rs/Quintal",
    "variety": "MCU 5"
  },
  "2010-10-09": {
    "min": 3700.0,
    "max": 4200.0,
    "modal": 4000.0,
    "arrival": 1.0,
    "arrive_unit": "Tonnes",
    "price_unit": "Rs/Quintal",
    "variety": "MCU 5"
  },
  "2010-10-10": {
    "min": 4000.0,
    "max": 4200.0,
    "modal": 4100.0,
    "arrival": 1.0,
    "arrive_unit": "Tonnes",
    "price_unit": "Rs/Quintal",
    "variety": "MCU 5"
  },
  "2010-10-11": {
    "min": 4000.0,
    "max": 4200.0,
    "modal": 4100.0,
    "arrival": 1.0,
    "arrive_unit": "Tonnes",
    "price_unit": "Rs/Quintal",
    "variety": "MCU 5"
  },
  "2010-10-12": {
    "min": 3980.0,
    "max": 4200.0,
    "modal": 4000.0,
    "arrival": 1.0,
    "arrive_unit": "Tonnes",
    "price_unit": "Rs/Quintal",
    "variety": "MCU 5"
  },
  "2010-10-13": {
    "min": 4000.0,
    "max": 4200.0,
    "modal": 4100.0,
    "arrival": 1.0,
    "arrive_unit": "Tonnes",
    "price_unit": "Rs/Quintal",
    "variety": "MCU 5"
  },
  "2010-10-14": {
    "min": 3800.0,
    "max": 4200.0,
    "modal": 4000.0,
    "arrival": 1.0,
    "arrive_unit": "Tonnes",
    "price_unit": "Rs/Quintal",
    "variety": "MCU 5"
  },
  "2010-10-15": {
    "min": 4000.0,
    "max": 4200.0,
    "modal": 4100.0,
    "arrival": 1.0,
    "arrive_unit": "Tonnes",
    "price_unit": "Rs/Quintal",
    "variety": "MCU 5"
  }
}