{
  "2013-02-01": {
    "min": 0.0,
    "max": 0.0,
    "modal": 3775.0,
    "arrival": 10.0,
    "arrive_unit": "Tonnes",
    "price_unit": "Rs/Quintal",
    "variety": "Other"
  },
  "2013-02-02": {
    "min": 0.0,
    "max": 0.0,
    "modal": 3700.0,
    "arrival": 10.5,
    "arrive_unit": "Tonnes",
    "price_unit": "Rs/Quintal",
    "variety": "Other"
  },
  "2013-02-04": {
    "min": 0.0,
    "max": 0.0,
    "modal": 3700.0,
    "arrival": 11.5,
    "arrive_unit": "Tonnes",
    "price_unit": "Rs/Quintal",
    "variety": "Other"
  },
  "2013-02-05": {
    "min": 0.0,
    "max": 0.0,
    "modal": 3675.0,
    "arrival": 12.5,
    "arrive_unit": "Tonnes",
    "price_unit": "Rs/Quintal",
    "variety": "Other"
  },
  "2013-02-06": {
    "min": 0.0,
    "max": 0.0,
    "modal": 3675.0,
    "arrival": 15.0,
    "arrive_unit": "Tonnes",
    "price_unit": "Rs/Quintal",
    "variety": "Other"
  },
  "2013-02-07": {
    "min": 0.0,
    "max": 0.0,
    "modal": 3665.0,
    "arrival": 16.0,
    "arrive_unit": "Tonnes",
    "price_unit": "Rs/Quintal",
    "variety": "Other"
  },
  "2013-02-08": {
    "min": 0.0,
    "max": 0.0,
    "modal": 3665.0,
    "arrival": 17.5,
    "arrive_unit": "Tonnes",
    "price_unit": "Rs/Quintal",
    "variety": "Other"
  },
  "2013-02-09": {
    "min": 0.0,
    "max": 0.0,
    "modal": 3660.0,
    "arrival": 16.0,
    "arrive_unit": "Tonnes",
    "price_unit": "Rs/Quintal",
    "variety": "Other"
  },
  "2013-02-11": {
    "min": 0.0,
    "max": 0.0,
    "modal": 3660.0,
    "arrival": 15.0,
    "arrive_unit": "Tonnes",
    "price_unit": "Rs/Quintal",
    "variety": "Other"
  },
  "2013-02-12": {
    "min": 0.0,
    "max": 0.0,
    "modal": 3640.0,
    "arrival": 16.0,
    "arrive_unit": "Tonnes",
    "price_unit": "Rs/Quintal",
    "variety": "Other"
  },
  "2013-02-13": {
    "min": 0.0,
    "max": 0.0,
    "modal": 3640.0,
    "arrival": 17.5,
    "arrive_unit": "Tonnes",
    "price_unit": "Rs/Quintal",
    "variety": "Other"
  },
  "2013-02-14": {
    "min": 0.0,
    "max": 0.0,
    "modal": 3600.0,
    "arrival": 14.0,
    "arrive_unit": "Tonnes",
    "price_unit": "Rs/Quintal",
    "variety": "Other"
  },
  "2013-02-15": {
    "min": 0.0,
    "max": 0.0,
    "modal": 3600.0,
    "arrival": 13.8,
    "arrive_unit": "Tonnes",
    "price_unit": "Rs/Quintal",
    "variety": "Other"
  },
  "2013-02-16": {
    "min": 0.0,
    "max": 0.0,
    "modal": 3585.0,
    "arrival": 14.0,
    "arrive_unit": "Tonnes",
    "price_unit": "Rs/Quintal",
    "variety": "Other"
  },
  "2013-02-18": {
    "min": 0.0,
    "max": 0.0,
    "modal": 3585.0,
    "arrival": 12.5,
    "arrive_unit": "Tonnes",
    "price_unit": "Rs/Quintal",
    "variety": "Other"
  },
  "2013-02-19": {
    "min": 0.0,
    "max": 0.0,
    "modal": 3525.0,
    "arrival": 12.7,
    "arrive_unit": "Tonnes",
    "price_unit": "Rs/Quintal",
    "variety": "Other"
  },
  "2013-02-20": {
    "min": 0.0,
    "max": 0.0,
    "modal": 3500.0,
    "arrival": 13.5,
    "arrive_unit": "Tonnes",
    "price_unit": "Rs/Quintal",
    "variety": "Other"
  },
  "2013-02-21": {
    "min": 0.0,
    "max": 0.0,
    "modal": 3500.0,
    "arrival": 12.5,
    "arrive_unit": "Tonnes",
    "price_unit": "Rs/Quintal",
    "variety": "Other"
  },
  "2013-02-22": {
    "min": 0.0,
    "max": 0.0,
    "modal": 3500.0,
    "arrival": 13.5,
    "arrive_unit": "Tonnes",
    "price_unit": "Rs/Quintal",
    "variety": "Other"
  },
  "2013-02-23": {
    "min": 0.0,
    "max": 0.0,
    "modal": 3480.0,
    "arrival": 14.5,
    "arrive_unit": "Tonnes",
    "price_unit": "Rs/Quintal",
    "variety": "Other"
  },
  "2013-02-25": {
    "min": 0.0,
    "max": 0.0,
    "modal": 3480.0,
    "arrival": 12.5,
    "arrive_unit": "Tonnes",
    "price_unit": "Rs/Quintal",
    "variety": "Other"
  },
  "2013-02-26": {
    "min": 0.0,
    "max": 0.0,
    "modal": 3475.0,
    "arrival": 13.0,
    "arrive_unit": "Tonnes",
    "price_unit": "Rs/Quintal",
    "variety": "Other"
  },
  "2013-02-27": {
    "min": 0.0,
    "max": 0.0,
    "modal": 3475.0,
    "arrival": 10.0,
    "arrive_unit": "Tonnes",
    "price_unit": "Rs/Quintal",
    "variety": "Other"
  },
  "2013-02-28": {
    "min": 0.0,
    "max": 0.0,
    "modal": 3470.0,
    "arrival": 10.5,
    "arrive_unit": "Tonnes",
    "price_unit": "Rs/Quintal",
    "variety": "Other"
  }
}