{
  "2014-07-04": {
    "min": 0.0,
    "max": 0.0,
    "modal": 1500.0,
    "arrival": 40.0,
    "arrive_unit": "Tonnes",
    "price_unit": "Rs/Quintal",
    "variety": "Local"
  },
  "2014-07-11": {
    "min": 0.0,
    "max": 0.0,
    "modal": 1480.0,
    "arrival": 45.0,
    "arrive_unit": "Tonnes",
    "price_unit": "Rs/Quintal",
    "variety": "Local"
  },
  "2014-07-18": {
    "min": 0.0,
    "max": 0.0,
    "modal": 1460.0,
    "arrival": 48.0,
    "arrive_unit": "Tonnes",
    "price_unit": "Rs/Quintal",
    "variety": "Local"
  },
  "2014-07-25": {
    "min": 0.0,
    "max": 0.0,
    "modal": 1450.0,
    "arrival": 50.0,
    "arrive_unit": "Tonnes",
    "price_unit": "Rs/Quintal",
    "variety": "Local"
  }
}