{
  "2010-05-18": {
    "min": 950.0,
    "max": 980.0,
    "modal": 960.0,
    "arrival": 2.5,
    "arrive_unit": "Tonnes",
    "price_unit": "Rs/Quintal",
    "variety": "Paddy fine"
  },
  "2010-05-19": {
    "min": 950.0,
    "max": 980.0,
    "modal": 960.0,
    "arrival": 36.5,
    "arrive_unit": "Tonnes",
    "price_unit": "Rs/Quintal",
    "variety": "Paddy fine"
  },
  "2010-05-20": {
    "min": 950.0,
    "max": 980.0,
    "modal": 960.0,
    "arrival": 30.0,
    "arrive_unit": "Tonnes",
    "price_unit": "Rs/Quintal",
    "variety": "Paddy fine"
  },
  "2010-05-21": {
    "min": 950.0,
    "max": 980.0,
    "modal": 960.0,
    "arrival": 13.0,
    "arrive_unit": "Tonnes",
    "price_unit": "Rs/Quintal",
    "variety": "Paddy fine"
  },
  "2010-05-22": {
    "min": 950.0,
    "max": 980.0,
    "modal": 960.0,
    "arrival": 6.5,
    "arrive_unit": "Tonnes",
    "price_unit": "Rs/Quintal",
    "variety": "Paddy fine"
  },
  "2010-05-23": {
    "min": 950.0,
    "max": 980.0,
    "modal": 960.0,
    "arrival": 2.0,
    "arrive_unit": "Tonnes",
    "price_unit": "Rs/Quintal",
    "variety": "Paddy fine"
  },
  "2010-05-26": {
    "min": 950.0,
    "max": 980.0,
    "modal": 960.0,
    "arrival": 2.0,
    "arrive_unit": "Tonnes",
    "price_unit": "Rs/Quintal",
    "variety": "Paddy fine"
  },
  "2010-05-27": {
    "min": 950.0,
    "max": 980.0,
    "modal": 960.0,
    "arrival": 4.0,
    "arrive_unit": "Tonnes",
    "price_unit": "Rs/Quintal",
    "variety": "Paddy fine"
  },
  "2010-05-28": {
    "min": 950.0,
    "max": 980.0,
    "modal": 960.0,
    "arrival": 2.0,
    "arrive_unit": "Tonnes",
    "price_unit": "Rs/Quintal",
    "variety": "Paddy fine"
  },
  "2010-05-29": {
    "min": 950.0,
    "max": 980.0,
    "modal": 960.0,
    "arrival": 4.0,
    "arrive_unit": "Tonnes",
    "price_unit": "Rs/Quintal",
    "variety": "Paddy fine"
  },
  "2010-05-31": {
    "min": 950.0,
    "max": 980.0,
    "modal": 960.0,
    "arrival": 6.5,
    "arrive_unit": "Tonnes",
    "price_unit": "Rs/Quintal",
    "variety": "Paddy fine"
  }
}